libcoveoc4ids/__init__.py
libcoveoc4ids/__main__.py
libcoveoc4ids/additional_checks.py
libcoveoc4ids/api.py
libcoveoc4ids/common_checks.py
libcoveoc4ids/config.py
libcoveoc4ids/schema.py
libcoveoc4ids-0.9.0.dist-info/LICENSE
libcoveoc4ids-0.9.0.dist-info/METADATA
libcoveoc4ids-0.9.0.dist-info/WHEEL
libcoveoc4ids-0.9.0.dist-info/entry_points.txt
libcoveoc4ids-0.9.0.dist-info/top_level.txt
libcoveoc4ids-0.9.0.dist-info/RECORD
