Metadata-Version: 2.1
Name: libcoveoc4ids
Version: 0.9.0
Summary: A data review library for the Open Contracting for Infrastructure Data Standards (OC4IDS)
Author-email: Open Contracting Partnership and Open Data Services Co-operative Limited <data@open-contracting.org>
License: AGPL-3.0-or-later
Project-URL: Homepage, https://github.com/open-contracting/lib-cove-oc4ids
Classifier: License :: OSI Approved :: GNU Affero General Public License v3 or later (AGPLv3+)
Classifier: Operating System :: MacOS
Classifier: Operating System :: POSIX :: Linux
Classifier: Programming Language :: Python :: 3.9
Classifier: Programming Language :: Python :: 3.10
Classifier: Programming Language :: Python :: 3.11
Classifier: Programming Language :: Python :: 3.12
Classifier: Programming Language :: Python :: Implementation :: CPython
License-File: LICENSE
Requires-Dist: click
Requires-Dist: libcove>=0.32
Requires-Dist: libcoveocds<0.17,>=0.12.7
Provides-Extra: perf
Requires-Dist: orjson>=3; extra == "perf"
Provides-Extra: test
Requires-Dist: coverage; extra == "test"
Requires-Dist: pytest; extra == "test"
